pypi_lever_lib/__init__.py
pypi_lever_lib/pypi_lever_lib.py
pypi_lever_lib-0.0.1.dist-info/DESCRIPTION.rst
pypi_lever_lib-0.0.1.dist-info/METADATA
pypi_lever_lib-0.0.1.dist-info/RECORD
pypi_lever_lib-0.0.1.dist-info/WHEEL
pypi_lever_lib-0.0.1.dist-info/metadata.json
pypi_lever_lib-0.0.1.dist-info/top_level.txt
