Metadata-Version: 2.0
Name: pypi-lever-lib
Version: 0.0.1
Summary: A small example package
Home-page: https://github.com/PepperPapa/xinNotes
Author: liu.changsheng
Author-email: mail_lcs@126.com
License: UNKNOWN
Platform: UNKNOWN
Classifier: Programming Language :: Python :: 3
Classifier: License :: OSI Approved :: MIT License
Classifier: Operating System :: OS Independent
